{
  "title": "Verdi ruft zu Warnstreiks im deutschen Einzelhandel auf",
  "translated_title": "Verdi Calls for Warning Strikes in German Retail Sector",
  "text": [
    {
      "text": "Am 15. Mai 2026 hat die Gewerkschaft Verdi bundesweite Warnstreiks im Einzel- und Großhandel ausgerufen.",
      "translated_text": "On 15 May 2026, the trade union Verdi called nationwide warning strikes in the retail and wholesale sector."
    },
    {
      "text": "Es sind die ersten solchen Streiks auf nationaler Ebene in dieser Branche seit vielen Jahren.",
      "translated_text": "These are the first such strikes at national level in this sector for many years."
    },
    {
      "text": "Verdi lehnt das neueste Angebot der Arbeitgeber ab.",
      "translated_text": "Verdi has rejected the employers' latest offer."
    },
    {
      "text": "Die Arbeitgeber boten eine Lohnerhöhung von zwei Prozent in diesem Jahr und 1,5 Prozent im August 2027 an.",
      "translated_text": "The employers offered a wage increase of two percent this year and 1.5 percent in August 2027."
    },
    {
      "text": "Die Gewerkschaft fordert dagegen sieben Prozent mehr Lohn oder mindestens 225 Euro mehr im Monat.",
      "translated_text": "The trade union, on the other hand, is demanding seven percent more pay or at least 225 euros more per month."
    },
    {
      "text": "Streikkundgebungen fanden in vielen deutschen Städten statt, unter anderem in Frankfurt am Main, Hamburg, Stuttgart und Dortmund.",
      "translated_text": "Strike rallies took place in many German cities, including Frankfurt am Main, Hamburg, Stuttgart, and Dortmund."
    },
    {
      "text": "Die Aktion betrifft Hunderttausende von Beschäftigten in Supermärkten und Geschäften.",
      "translated_text": "The action affects hundreds of thousands of employees in supermarkets and shops."
    },
    {
      "text": "Es wird erwartet, dass es in vielen Filialen zu deutlichen Störungen kommt.",
      "translated_text": "Significant disruptions are expected in many branches."
    },
    {
      "text": "Der Tarifstreit geht bereits seit mehreren Monaten ohne Einigung.",
      "translated_text": "The pay dispute has been going on for several months without a resolution."
    },
    {
      "text": "Verdi sagt, die Reallöhne der Beschäftigten im Handel sind in den letzten Jahren gesunken.",
      "translated_text": "Verdi says the real wages of retail workers have fallen in recent years."
    },
    {
      "text": "Die Gewerkschaft macht die Inflation und die gestiegenen Lebenshaltungskosten für die hohe Forderung verantwortlich.",
      "translated_text": "The trade union blames inflation and rising living costs for the high demand."
    },
    {
      "text": "Falls keine Einigung erzielt wird, droht Verdi mit weiteren und längeren Streiks.",
      "translated_text": "If no agreement is reached, Verdi is threatening further and longer strikes."
    },
    {
      "text": "Die nächste Verhandlungsrunde ist für Ende Mai geplant.",
      "translated_text": "The next round of negotiations is planned for the end of May."
    }
  ],
  "key_vocab": [
    {
      "term": "der Warnstreik",
      "translated_term": "the warning strike",
      "example_usage": "Verdi hat bundesweite Warnstreiks im Einzel- und Großhandel ausgerufen."
    },
    {
      "term": "der Einzelhandel",
      "translated_term": "the retail sector",
      "example_usage": "Die Aktion betrifft Hunderttausende von Beschäftigten im Einzelhandel."
    },
    {
      "term": "die Lohnerhöhung",
      "translated_term": "the wage increase",
      "example_usage": "Die Arbeitgeber boten eine Lohnerhöhung von zwei Prozent an."
    },
    {
      "term": "ablehnen",
      "translated_term": "to reject / to decline",
      "example_usage": "Verdi lehnt das neueste Angebot der Arbeitgeber ab."
    },
    {
      "term": "die Lebenshaltungskosten",
      "translated_term": "the cost of living",
      "example_usage": "Die Gewerkschaft macht die gestiegenen Lebenshaltungskosten für die hohe Forderung verantwortlich."
    },
    {
      "term": "drohen",
      "translated_term": "to threaten",
      "example_usage": "Falls keine Einigung erzielt wird, droht Verdi mit weiteren Streiks."
    }
  ],
  "tags": [
    {
      "name": "Streik",
      "translated_name": "Strike"
    },
    {
      "name": "Deutschland",
      "translated_name": "Germany"
    },
    {
      "name": "Arbeitspolitik",
      "translated_name": "Labor Policy"
    }
  ],
  "sources": [
    {
      "name": "FashionNetwork: Calls rise for warning strikes across Germany's retail sector",
      "link_url": "https://ww.fashionnetwork.com/news/Calls-rise-for-warning-strikes-across-germany-s-retail-sector,1832120.html"
    }
  ]
}
