{
  "title": "Renten in Deutschland steigen ab Juli 2026 um 4,24 Prozent",
  "translated_title": "Pensions in Germany Rise by 4.24 Percent from July 2026",
  "text": [
    {
      "text": "Ab dem 1. Juli 2026 bekommen rund 21 Millionen Rentnerinnen und Rentner in Deutschland mehr Geld.",
      "translated_text": "From 1 July 2026, around 21 million pensioners in Germany will receive more money."
    },
    {
      "text": "Die Renten steigen um 4,24 Prozent.",
      "translated_text": "Pensions will rise by 4.24 percent."
    },
    {
      "text": "Bundesarbeitsministerin Bärbel Bas von der SPD hat die Erhöhung im März bekannt gegeben.",
      "translated_text": "Federal Labour Minister Bärbel Bas from the SPD announced the increase in March."
    },
    {
      "text": "Sie sagte, dass die gute Lohnentwicklung zu einer deutlichen Rentenanpassung führe.",
      "translated_text": "She said that the positive wage development was leading to a noticeable pension adjustment."
    },
    {
      "text": "Der aktuelle Rentenwert steigt von 40,79 Euro auf 42,52 Euro.",
      "translated_text": "The current pension value rises from 40.79 euros to 42.52 euros."
    },
    {
      "text": "Wer 45 Jahre lang den Durchschnittslohn verdient hat, bekommt monatlich 77,85 Euro mehr.",
      "translated_text": "Those who earned an average salary for 45 years will receive an additional 77.85 euros per month."
    },
    {
      "text": "Die Rentenerhöhung folgt einem festen System: Die Renten werden an die Lohnentwicklung angepasst.",
      "translated_text": "The pension increase follows a fixed system: pensions are adjusted in line with wage developments."
    },
    {
      "text": "In den letzten Jahren sind die Löhne in Deutschland stark gestiegen.",
      "translated_text": "In recent years, wages in Germany have risen significantly."
    },
    {
      "text": "Deshalb steigen auch die Renten deutlich an.",
      "translated_text": "As a result, pensions are also rising noticeably."
    },
    {
      "text": "Viele Rentnerinnen und Rentner freuen sich über die Erhöhung, da auch die Lebenshaltungskosten gestiegen sind.",
      "translated_text": "Many pensioners are pleased about the increase, as the cost of living has also risen."
    },
    {
      "text": "Das Kabinett hat der Rentenerhöhung bereits zugestimmt.",
      "translated_text": "The cabinet has already approved the pension increase."
    },
    {
      "text": "Nun muss noch der Bundesrat zustimmen.",
      "translated_text": "The Bundesrat still needs to give its approval."
    },
    {
      "text": "Kritiker warnen jedoch, dass das Rentensystem langfristig reformiert werden muss.",
      "translated_text": "However, critics warn that the pension system needs to be reformed in the long term."
    },
    {
      "text": "Der Grund ist der demografische Wandel: Es gibt immer mehr ältere Menschen und immer weniger junge Beitragszahler.",
      "translated_text": "The reason is demographic change: there are ever more older people and ever fewer young contributors."
    },
    {
      "text": "Die Bundesregierung plant deshalb weitere Reformen des Rentensystems in den kommenden Jahren.",
      "translated_text": "The federal government is therefore planning further reforms of the pension system in the coming years."
    }
  ],
  "key_vocab": [
    {
      "term": "die Rentenerhöhung",
      "translated_term": "the pension increase",
      "example_usage": "Viele Rentnerinnen und Rentner freuen sich über die Erhöhung, da auch die Lebenshaltungskosten gestiegen sind."
    },
    {
      "term": "der Rentenwert",
      "translated_term": "the pension value",
      "example_usage": "Der aktuelle Rentenwert steigt von 40,79 Euro auf 42,52 Euro."
    },
    {
      "term": "die Rentenanpassung",
      "translated_term": "the pension adjustment",
      "example_usage": "Die gute Lohnentwicklung führe zu einer deutlichen Rentenanpassung."
    },
    {
      "term": "der demografische Wandel",
      "translated_term": "the demographic change",
      "example_usage": "Der Grund ist der demografische Wandel: Es gibt immer mehr ältere Menschen und immer weniger junge Beitragszahler."
    },
    {
      "term": "der Beitragszahler",
      "translated_term": "the contributor (to social insurance)",
      "example_usage": "Es gibt immer mehr ältere Menschen und immer weniger junge Beitragszahler."
    },
    {
      "term": "zustimmen",
      "translated_term": "to approve / to agree",
      "example_usage": "Nun muss noch der Bundesrat zustimmen."
    }
  ],
  "tags": [
    {
      "name": "Sozialpolitik",
      "translated_name": "Social Policy"
    },
    {
      "name": "Deutschland",
      "translated_name": "Germany"
    },
    {
      "name": "Deutsche Politik",
      "translated_name": "German Politics"
    }
  ],
  "sources": [
    {
      "name": "iamexpat.de: German pensions to rise by 4.24 percent in July",
      "link_url": "https://www.iamexpat.de/expat-info/germany-news/german-pensions-rise-424-percent-july"
    },
    {
      "name": "newsworm.de: Cabinet Approves 4.24% Pension Increase Starting July 2026",
      "link_url": "https://www.newsworm.de/news/cabinet-approves-4-24-pension-increase-starting-july-2026"
    },
    {
      "name": "Pension Policy International: German pensions to rise by 4.24 percent in July",
      "link_url": "https://www.pensionpolicyinternational.com/german-pensions-to-rise-by-424-percent-in-july/"
    }
  ]
}
