{
  "title": "Internationaler Tag der Frauen und Mädchen in der Wissenschaft",
  "translated_title": "International Day of Women and Girls in Science",
  "text": [
    {
      "text": "Heute, am 11. Februar, ist der Internationale Tag der Frauen und Mädchen in der Wissenschaft.",
      "translated_text": "Today, on February 11, is the International Day of Women and Girls in Science."
    },
    {
      "text": "Die Vereinten Nationen haben diesen Tag im Jahr 2015 eingeführt.",
      "translated_text": "The United Nations established this day in 2015."
    },
    {
      "text": "Das Ziel ist es, mehr Gleichberechtigung in den MINT-Fächern zu erreichen.",
      "translated_text": "The goal is to achieve more equality in STEM subjects."
    },
    {
      "text": "MINT steht für Mathematik, Informatik, Naturwissenschaften und Technik.",
      "translated_text": "STEM stands for Science, Technology, Engineering, and Mathematics."
    },
    {
      "text": "Das Thema des Jahres 2026 lautet 'Vision zu Wirkung: MINT neu definieren durch Schließung der Geschlechterlücke'.",
      "translated_text": "The theme for 2026 is 'Vision to Impact: Redefining STEM by Closing the Gender Gap'."
    },
    {
      "text": "Weltweit arbeiten immer noch mehr Männer als Frauen in wissenschaftlichen Berufen.",
      "translated_text": "Worldwide, there are still more men than women working in scientific professions."
    },
    {
      "text": "Viele Mädchen und junge Frauen entscheiden sich gegen eine Karriere in der Wissenschaft.",
      "translated_text": "Many girls and young women decide against a career in science."
    },
    {
      "text": "Die Gründe dafür sind vielfältig: soziale Vorurteile, fehlende Vorbilder und ungleiche Chancen.",
      "translated_text": "The reasons for this are varied: social prejudices, lack of role models, and unequal opportunities."
    },
    {
      "text": "An diesem Tag finden weltweit Veranstaltungen statt.",
      "translated_text": "Events take place worldwide on this day."
    },
    {
      "text": "Schulen, Universitäten und Forschungseinrichtungen präsentieren die Arbeit von Wissenschaftlerinnen.",
      "translated_text": "Schools, universities, and research institutions present the work of female scientists."
    },
    {
      "text": "Sie wollen junge Frauen ermutigen, eine wissenschaftliche Laufbahn einzuschlagen.",
      "translated_text": "They want to encourage young women to pursue a scientific career."
    },
    {
      "text": "Experten betonen, dass Wissenschaft von Vielfalt profitiert.",
      "translated_text": "Experts emphasize that science benefits from diversity."
    }
  ],
  "key_vocab": [
    {
      "term": "die Vereinten Nationen",
      "translated_term": "United Nations",
      "example_usage": "Die Vereinten Nationen haben diesen Tag im Jahr 2015 eingeführt."
    },
    {
      "term": "einführen",
      "translated_term": "to introduce, to establish",
      "example_usage": "Die Vereinten Nationen haben diesen Tag im Jahr 2015 eingeführt."
    },
    {
      "term": "die Gleichberechtigung",
      "translated_term": "equality, equal rights",
      "example_usage": "Das Ziel ist es, mehr Gleichberechtigung in den MINT-Fächern zu erreichen."
    },
    {
      "term": "das MINT-Fach",
      "translated_term": "STEM subject",
      "example_usage": "Das Ziel ist es, mehr Gleichberechtigung in den MINT-Fächern zu erreichen."
    },
    {
      "term": "die Geschlechterlücke",
      "translated_term": "gender gap",
      "example_usage": "Das Thema des Jahres 2026 lautet 'Vision zu Wirkung: MINT neu definieren durch Schließung der Geschlechterlücke'."
    },
    {
      "term": "der wissenschaftliche Beruf",
      "translated_term": "scientific profession",
      "example_usage": "Weltweit arbeiten immer noch mehr Männer als Frauen in wissenschaftlichen Berufen."
    },
    {
      "term": "sich entscheiden",
      "translated_term": "to decide",
      "example_usage": "Viele Mädchen und junge Frauen entscheiden sich gegen eine Karriere in der Wissenschaft."
    },
    {
      "term": "vielfältig",
      "translated_term": "diverse, varied",
      "example_usage": "Die Gründe dafür sind vielfältig: soziale Vorurteile, fehlende Vorbilder und ungleiche Chancen."
    },
    {
      "term": "das Vorurteil",
      "translated_term": "prejudice, bias",
      "example_usage": "Die Gründe dafür sind vielfältig: soziale Vorurteile, fehlende Vorbilder und ungleiche Chancen."
    },
    {
      "term": "das Vorbild",
      "translated_term": "role model",
      "example_usage": "Die Gründe dafür sind vielfältig: soziale Vorurteile, fehlende Vorbilder und ungleiche Chancen."
    },
    {
      "term": "die Forschungseinrichtung",
      "translated_term": "research institution",
      "example_usage": "Schulen, Universitäten und Forschungseinrichtungen präsentieren die Arbeit von Wissenschaftlerinnen."
    },
    {
      "term": "ermutigen",
      "translated_term": "to encourage",
      "example_usage": "Sie wollen junge Frauen ermutigen, eine wissenschaftliche Laufbahn einzuschlagen."
    },
    {
      "term": "die Laufbahn",
      "translated_term": "career",
      "example_usage": "Sie wollen junge Frauen ermutigen, eine wissenschaftliche Laufbahn einzuschlagen."
    },
    {
      "term": "die Vielfalt",
      "translated_term": "diversity",
      "example_usage": "Experten betonen, dass Wissenschaft von Vielfalt profitiert."
    }
  ],
  "tags": [
    {
      "name": "Internationale Nachrichten",
      "translated_name": "International News"
    },
    {
      "name": "Wissenschaft",
      "translated_name": "Science"
    },
    {
      "name": "Vereinte Nationen",
      "translated_name": "United Nations"
    }
  ],
  "sources": [
    {
      "name": "Zee News",
      "link_url": "https://zeenews.india.com/education/international-day-of-women-and-girls-in-science-in-2026-3015532.html"
    },
    {
      "name": "Current Affairs Cloud",
      "link_url": "https://affairscloud.com/current-affairs-11-february-2026/"
    },
    {
      "name": "Euronews",
      "link_url": "https://www.euronews.com/video/2026/02/11/latest-news-bulletin-february-11th-2026-morning"
    }
  ]
}
