{
  "title": "Deutschland baut Europas stärkste Armee auf",
  "translated_title": "Germany Builds Europe's Strongest Army",
  "text": [
    {
      "text": "Deutschland arbeitet daran, die stärkste konventionelle Armee in Europa aufzubauen.",
      "translated_text": "Germany is working to build the strongest conventional army in Europe."
    },
    {
      "text": "Bundeskanzler Friedrich Merz hat erklärt, dass Deutschland in eine neue Ära eingetreten ist.",
      "translated_text": "Chancellor Friedrich Merz has stated that Germany has entered a new era."
    },
    {
      "text": "In einer wichtigen Rede sagte er: \"Wir sind in eine Ära der Großmachtpolitik eingetreten.\"",
      "translated_text": "In an important speech, he said: 'We have entered an era of great power politics.'"
    },
    {
      "text": "Merz betonte, dass die neue Welt auf Macht, Stärke und notfalls Gewalt basiert.",
      "translated_text": "Merz emphasized that the new world is based on power, strength and, if necessary, force."
    },
    {
      "text": "Diese Aussagen markieren einen wichtigen Wandel in der deutschen Sicherheitspolitik.",
      "translated_text": "These statements mark an important shift in German security policy."
    },
    {
      "text": "Deutschland hat historisch eine eher zurückhaltende militärische Position eingenommen.",
      "translated_text": "Germany has historically taken a rather restrained military position."
    },
    {
      "text": "Aber die internationale Lage hat sich verändert.",
      "translated_text": "But the international situation has changed."
    },
    {
      "text": "Die Bundeswehr soll massiv ausgebaut und modernisiert werden.",
      "translated_text": "The Bundeswehr is to be massively expanded and modernized."
    },
    {
      "text": "Die Regierung plant große Investitionen in Verteidigungstechnologie.",
      "translated_text": "The government plans major investments in defense technology."
    },
    {
      "text": "Experten sehen darin eine Reaktion auf die wachsenden Spannungen in Europa.",
      "translated_text": "Experts see this as a response to growing tensions in Europe."
    },
    {
      "text": "Deutschland will mehr Verantwortung für die europäische Sicherheit übernehmen.",
      "translated_text": "Germany wants to take on more responsibility for European security."
    }
  ],
  "key_vocab": [
    {
      "term": "die Armee",
      "translated_term": "army",
      "example_usage": "Deutschland baut Europas stärkste Armee auf."
    },
    {
      "term": "konventionell",
      "translated_term": "conventional",
      "example_usage": "Deutschland arbeitet daran, die stärkste konventionelle Armee in Europa aufzubauen."
    },
    {
      "term": "die Ära",
      "translated_term": "era",
      "example_usage": "Bundeskanzler Friedrich Merz hat erklärt, dass Deutschland in eine neue Ära eingetreten ist."
    },
    {
      "term": "die Großmachtpolitik",
      "translated_term": "great power politics",
      "example_usage": "In einer wichtigen Rede sagte er: \"Wir sind in eine Ära der Großmachtpolitik eingetreten.\""
    },
    {
      "term": "betonen",
      "translated_term": "to emphasize",
      "example_usage": "Merz betonte, dass die neue Welt auf Macht, Stärke und notfalls Gewalt basiert."
    },
    {
      "term": "der Wandel",
      "translated_term": "shift/change",
      "example_usage": "Diese Aussagen markieren einen wichtigen Wandel in der deutschen Sicherheitspolitik."
    },
    {
      "term": "zurückhaltend",
      "translated_term": "restrained",
      "example_usage": "Deutschland hat historisch eine eher zurückhaltende militärische Position eingenommen."
    },
    {
      "term": "ausbauen",
      "translated_term": "to expand",
      "example_usage": "Die Bundeswehr soll massiv ausgebaut und modernisiert werden."
    },
    {
      "term": "die Spannung",
      "translated_term": "tension",
      "example_usage": "Experten sehen darin eine Reaktion auf die wachsenden Spannungen in Europa."
    },
    {
      "term": "die Verantwortung",
      "translated_term": "responsibility",
      "example_usage": "Deutschland will mehr Verantwortung für die europäische Sicherheit übernehmen."
    }
  ],
  "tags": [
    {
      "name": "Bundeswehr",
      "translated_name": "Federal Armed Forces"
    },
    {
      "name": "Verteidigung",
      "translated_name": "Defense"
    },
    {
      "name": "Deutsche Politik",
      "translated_name": "German Politics"
    }
  ],
  "sources": [
    {
      "name": "Al Jazeera",
      "link_url": "https://www.aljazeera.com/news/2026/1/19/why-is-germany-trying-to-build-europes-strongest-conventional-army"
    }
  ]
}
