{
  "title": "Demonstration für ein freies Iran am Brandenburger Tor",
  "translated_title": "Demonstration for a free Iran at the Brandenburg Gate",
  "text": [
    {
      "text": "Am Samstag, den 7. Februar 2026, findet am Brandenburger Tor in Berlin eine große Demonstration statt.",
      "translated_text": "On Saturday, February 7, 2026, a large demonstration is taking place at the Brandenburg Gate in Berlin."
    },
    {
      "text": "Die Demonstration beginnt um 13:00 Uhr und wird vom iranischen Widerstand organisiert.",
      "translated_text": "The demonstration starts at 1:00 PM and is organized by the Iranian Resistance."
    },
    {
      "text": "Die Menschen demonstrieren für Freiheit und Demokratie im Iran.",
      "translated_text": "The people are demonstrating for freedom and democracy in Iran."
    },
    {
      "text": "Sie protestieren gegen das autoritäre Regime in ihrem Heimatland.",
      "translated_text": "They are protesting against the authoritarian regime in their homeland."
    },
    {
      "text": "Trotz eisiger Temperaturen von minus 18 Grad Celsius versammelten sich bereits am Vortag viele Menschen.",
      "translated_text": "Despite freezing temperatures of minus 18 degrees Celsius, many people already gathered the day before."
    },
    {
      "text": "Sie wollten die Märtyrer des iranischen Aufstands ehren.",
      "translated_text": "They wanted to honor the martyrs of the Iranian uprising."
    },
    {
      "text": "Die Organisatoren erwarten Tausende Teilnehmer aus verschiedenen europäischen Ländern.",
      "translated_text": "The organizers expect thousands of participants from various European countries."
    },
    {
      "text": "Die Demonstration steht unter dem Motto 'Nein zum Schah, Nein zu den Mullahs'.",
      "translated_text": "The demonstration is under the motto 'No to the Shah, No to the Mullahs'."
    },
    {
      "text": "Dies zeigt, dass die Demonstranten sowohl die alte Monarchie als auch das heutige Regime ablehnen.",
      "translated_text": "This shows that the demonstrators reject both the old monarchy and today's regime."
    },
    {
      "text": "Die iranische Gemeinschaft in Deutschland möchte internationale Unterstützung für die Freiheitsbewegung gewinnen.",
      "translated_text": "The Iranian community in Germany wants to gain international support for the freedom movement."
    }
  ],
  "key_vocab": [
    {
      "term": "die Demonstration",
      "translated_term": "demonstration, protest",
      "example_usage": "Am Samstag findet am Brandenburger Tor eine große Demonstration statt."
    },
    {
      "term": "das Brandenburger Tor",
      "translated_term": "Brandenburg Gate",
      "example_usage": "Die Demonstration findet am Brandenburger Tor in Berlin statt."
    },
    {
      "term": "der Widerstand",
      "translated_term": "resistance",
      "example_usage": "Die Demonstration wird vom iranischen Widerstand organisiert."
    },
    {
      "term": "organisieren",
      "translated_term": "to organize",
      "example_usage": "Die Demonstration wird vom iranischen Widerstand organisiert."
    },
    {
      "term": "demonstrieren für",
      "translated_term": "to demonstrate for",
      "example_usage": "Die Menschen demonstrieren für Freiheit und Demokratie im Iran."
    },
    {
      "term": "protestieren gegen",
      "translated_term": "to protest against",
      "example_usage": "Sie protestieren gegen das autoritäre Regime in ihrem Heimatland."
    },
    {
      "term": "das Regime",
      "translated_term": "regime",
      "example_usage": "Sie protestieren gegen das autoritäre Regime."
    },
    {
      "term": "das Heimatland",
      "translated_term": "homeland",
      "example_usage": "Sie protestieren gegen das Regime in ihrem Heimatland."
    },
    {
      "term": "sich versammeln",
      "translated_term": "to gather, to assemble",
      "example_usage": "Viele Menschen versammelten sich bereits am Vortag."
    },
    {
      "term": "der Märtyrer",
      "translated_term": "martyr",
      "example_usage": "Sie wollten die Märtyrer des iranischen Aufstands ehren."
    },
    {
      "term": "ehren",
      "translated_term": "to honor",
      "example_usage": "Sie wollten die Märtyrer ehren."
    },
    {
      "term": "der Aufstand",
      "translated_term": "uprising, revolt",
      "example_usage": "Sie wollten die Märtyrer des iranischen Aufstands ehren."
    },
    {
      "term": "das Motto",
      "translated_term": "motto, slogan",
      "example_usage": "Die Demonstration steht unter dem Motto 'Nein zum Schah, Nein zu den Mullahs'."
    },
    {
      "term": "ablehnen",
      "translated_term": "to reject",
      "example_usage": "Die Demonstranten lehnen sowohl die alte Monarchie als auch das heutige Regime ab."
    },
    {
      "term": "die Gemeinschaft",
      "translated_term": "community",
      "example_usage": "Die iranische Gemeinschaft in Deutschland möchte internationale Unterstützung gewinnen."
    }
  ],
  "tags": [
    {
      "name": "Berlin",
      "translated_name": "Berlin"
    },
    {
      "name": "Iran",
      "translated_name": "Iran"
    },
    {
      "name": "Proteste",
      "translated_name": "Protests"
    },
    {
      "name": "Menschenrechte",
      "translated_name": "Human Rights"
    }
  ],
  "sources": [
    {
      "name": "Iran Freedom - Join the Berlin Free Iran Demonstration",
      "link_url": "https://iranfreedom.org/en/iranian-communities/2026/02/join-the-berlin-free-iran-demonstration-on-february-7-2026-no-to-shah-no-to-mullah/83517/"
    },
    {
      "name": "Iran Freedom - Berlin Demonstration Announcement",
      "link_url": "https://iranfreedom.org/en/news/2026/01/join-the-berlin-free-iran-demonstration-on-february-7-no-to-shah-no-to-mullah/83093/"
    }
  ]
}
