{
  "title": "Arbeitslosigkeit in Deutschland steigt auf Zwölfjahreshoch",
  "translated_title": "Unemployment in Germany Rises to Twelve-Year High",
  "text": [
    {
      "text": "Deutschland steht vor einer ernsthaften wirtschaftlichen Herausforderung.",
      "translated_text": "Germany faces a serious economic challenge."
    },
    {
      "text": "Die Arbeitslosenzahl hat die Marke von 3 Millionen Menschen überschritten.",
      "translated_text": "The unemployment figure has exceeded the mark of 3 million people."
    },
    {
      "text": "Dies ist der höchste Stand seit zwölf Jahren.",
      "translated_text": "This is the highest level in twelve years."
    },
    {
      "text": "Bundeskanzler Friedrich Merz hat erklärt, dass die Stärkung der Wirtschaft seine Priorität für 2026 ist.",
      "translated_text": "Chancellor Friedrich Merz has stated that strengthening the economy is his priority for 2026."
    },
    {
      "text": "Die wirtschaftliche Situation bereitet vielen Menschen und Unternehmen Sorgen.",
      "translated_text": "The economic situation worries many people and companies."
    },
    {
      "text": "Experten sehen mehrere Gründe für den Anstieg der Arbeitslosigkeit.",
      "translated_text": "Experts see several reasons for the increase in unemployment."
    },
    {
      "text": "Die globale Wirtschaftslage und der Strukturwandel spielen eine wichtige Rolle.",
      "translated_text": "The global economic situation and structural change play an important role."
    },
    {
      "text": "Die Regierung plant Maßnahmen zur Ankurbelung der Wirtschaft.",
      "translated_text": "The government is planning measures to boost the economy."
    },
    {
      "text": "Dazu gehören Investitionen in Infrastruktur und Innovation.",
      "translated_text": "These include investments in infrastructure and innovation."
    },
    {
      "text": "Viele hoffen, dass die Arbeitslosenzahl bald wieder sinken wird.",
      "translated_text": "Many hope that the unemployment figure will decrease again soon."
    }
  ],
  "key_vocab": [
    {
      "term": "die Herausforderung",
      "translated_term": "challenge",
      "example_usage": "Deutschland steht vor einer ernsthaften wirtschaftlichen Herausforderung."
    },
    {
      "term": "die Arbeitslosenzahl",
      "translated_term": "unemployment figure",
      "example_usage": "Die Arbeitslosenzahl hat die Marke von 3 Millionen Menschen überschritten."
    },
    {
      "term": "überschreiten",
      "translated_term": "to exceed",
      "example_usage": "Die Arbeitslosenzahl hat die Marke von 3 Millionen Menschen überschritten."
    },
    {
      "term": "der Stand",
      "translated_term": "level",
      "example_usage": "Dies ist der höchste Stand seit zwölf Jahren."
    },
    {
      "term": "die Stärkung",
      "translated_term": "strengthening",
      "example_usage": "Bundeskanzler Friedrich Merz hat erklärt, dass die Stärkung der Wirtschaft seine Priorität für 2026 ist."
    },
    {
      "term": "bereiten",
      "translated_term": "to cause (worry)",
      "example_usage": "Die wirtschaftliche Situation bereitet vielen Menschen und Unternehmen Sorgen."
    },
    {
      "term": "der Anstieg",
      "translated_term": "increase",
      "example_usage": "Experten sehen mehrere Gründe für den Anstieg der Arbeitslosigkeit."
    },
    {
      "term": "der Strukturwandel",
      "translated_term": "structural change",
      "example_usage": "Die globale Wirtschaftslage und der Strukturwandel spielen eine wichtige Rolle."
    },
    {
      "term": "ankurbeln",
      "translated_term": "to boost",
      "example_usage": "Die Regierung plant Maßnahmen zur Ankurbelung der Wirtschaft."
    },
    {
      "term": "sinken",
      "translated_term": "to decrease",
      "example_usage": "Viele hoffen, dass die Arbeitslosenzahl bald wieder sinken wird."
    }
  ],
  "tags": [
    {
      "name": "Wirtschaftspolitik",
      "translated_name": "Economic Policy"
    },
    {
      "name": "Arbeitspolitik",
      "translated_name": "Labor Policy"
    },
    {
      "name": "Deutschland",
      "translated_name": "Germany"
    }
  ],
  "sources": [
    {
      "name": "The Left Berlin",
      "link_url": "https://theleftberlin.com/news-from-berlin-and-germany-11th-february-2026/"
    }
  ]
}
